odoo8_addon_l10n_it_account_stamp-8.0.1.0.1-py3.6-nspkg.pth
odoo_addons/l10n_it_account_stamp/README.rst
odoo_addons/l10n_it_account_stamp/__init__.py
odoo_addons/l10n_it_account_stamp/__openerp__.py
odoo_addons/l10n_it_account_stamp/data/data.xml
odoo_addons/l10n_it_account_stamp/i18n/it.po
odoo_addons/l10n_it_account_stamp/i18n/l10n_it_account_stamp.pot
odoo_addons/l10n_it_account_stamp/models/__init__.py
odoo_addons/l10n_it_account_stamp/models/company.py
odoo_addons/l10n_it_account_stamp/models/invoice.py
odoo_addons/l10n_it_account_stamp/models/product.py
odoo_addons/l10n_it_account_stamp/readme/CONFIGURE.rst
odoo_addons/l10n_it_account_stamp/readme/CONTRIBUTORS.rst
odoo_addons/l10n_it_account_stamp/readme/DESCRIPTION.rst
odoo_addons/l10n_it_account_stamp/readme/USAGE.rst
odoo_addons/l10n_it_account_stamp/static/description/icon.png
odoo_addons/l10n_it_account_stamp/static/description/index.html
odoo_addons/l10n_it_account_stamp/views/company_view.xml
odoo_addons/l10n_it_account_stamp/views/invoice_view.xml
odoo_addons/l10n_it_account_stamp/views/product_view.xml
odoo8_addon_l10n_it_account_stamp-8.0.1.0.1.dist-info/METADATA
odoo8_addon_l10n_it_account_stamp-8.0.1.0.1.dist-info/WHEEL
odoo8_addon_l10n_it_account_stamp-8.0.1.0.1.dist-info/namespace_packages.txt
odoo8_addon_l10n_it_account_stamp-8.0.1.0.1.dist-info/top_level.txt
odoo8_addon_l10n_it_account_stamp-8.0.1.0.1.dist-info/RECORD
